[
  {"username": "root", "first_name": "Da", "last_name": "Master",
    "email": "christian.kuhl@dvbbank.com",
    "is_staff": true, "is_superuser": true,
    "groups": ["Admin", "Collateral Management", "Counterparty Risk",
                "Fair Value", "Hedge Accounting", "Liquidity Risk", "Market Risk"]},
  {"username": "schnh0", "first_name": "Heinz", "last_name": "Schneider",
    "email": "heinz.schneider@dvbbank.com",
    "is_staff": true, "is_superuser": false,
    "groups": ["Admin", "Collateral Management", "Counterparty Risk",
                "Fair Value", "Hedge Accounting", "Liquidity Risk", "Market Risk"]},
  {"username": "kuhlc0", "first_name": "Christian", "last_name": "Kuhl",
    "email": "christian.kuhl@dvbbank.com",
    "is_staff": false, "is_superuser": false,
    "groups": ["Fair Value", "Market Risk", "Crossover Reporting"]},
  {"username": "rehmc0", "first_name": "Christian", "last_name": "Rehm",
    "email": "christian.rehm@dvbbank.com",
    "is_staff": false, "is_superuser": false,
    "groups": ["Fair Value", "Crossover Reporting"]},
  {"username": "gartc0", "first_name": "Claudia", "last_name": "Gartner",
    "email": "claudia.gartner@dvbbank.com",
    "is_staff": false, "is_superuser": false,
    "groups": ["Market Risk", "Fair Value", "Crossover Reporting"]},
  {"username": "boesp0", "first_name": "Peter", "last_name": "Böshans",
    "email": "peter.boeshans@dvbbank.com",
    "is_staff": false, "is_superuser": false,
    "groups": ["Collateral Management", "Hedge Accounting", "Liquidity Risk", "Market Risk"]},
  {"username": "becka0", "first_name": "Andreas", "last_name": "Beck",
    "email": "andreas.beck@dvbbank.com",
    "is_staff": false, "is_superuser": false,
    "groups": ["Collateral Management", "Hedge Accounting", "Liquidity Risk", "Market Risk"]},
  {"username": "dzhea0", "first_name": "Aynara", "last_name": "Dzhentemirova",
    "email": "aynara.dzhentemirova@dvbbank.com",
    "is_staff": false, "is_superuser": false,
    "groups": ["Fair Value", "Liquidity Risk", "Market Risk"]},
  {"username": "natha0", "first_name": "Andrea", "last_name": "Nathmann",
    "email": "andrea.nathmann@dvbbank.com",
    "is_staff": false, "is_superuser": false,
    "groups": ["Counterparty Risk", "Liquidity Risk"]},
  {"username": "schuh0", "first_name": "Heike", "last_name": "Schumacher",
    "email": "heike.schumacher@dvbbank.com",
    "is_staff": false, "is_superuser": false,
    "groups": ["Liquidity Risk", "Crossover Reporting"]},
  {"username": "bangs0", "first_name": "Smriti", "last_name": "Bangar",
    "email": "smriti.bangar@dvbbank.com",
    "is_staff": false, "is_superuser": false,
    "groups": ["Market Risk"]}
]
